deepseek/__init__.py
deepseek/deepseek.py
deepseek_sdk-0.1.1.dist-info/licenses/LICENSE
deepseek_sdk-0.1.1.dist-info/METADATA
deepseek_sdk-0.1.1.dist-info/WHEEL
deepseek_sdk-0.1.1.dist-info/top_level.txt
deepseek_sdk-0.1.1.dist-info/RECORD
