Metadata-Version: 2.4
Name: deepseek-sdk
Version: 0.1.1
Summary: Python client for DeepSeek API
Home-page: https://github.com/Pro-Sifat-Hasan/deepseek-python
Author: Sifat Hasan
Author-email: sihabhossan633@gmail.com
Classifier: Programming Language :: Python :: 3
Classifier: License :: OSI Approved :: MIT License
Classifier: Operating System :: OS Independent
Requires-Python: >=3.8
License-File: LICENSE
Requires-Dist: openai>=1.0.0
Dynamic: license-file
